LICENSE.txt
MANIFEST.in
README.md
setup.py
pkulast/__init__.py
pkulast/api.py
pkulast/config.py
pkulast/constants.py
pkulast/exceptions.py
pkulast.egg-info/PKG-INFO
pkulast.egg-info/SOURCES.txt
pkulast.egg-info/dependency_links.txt
pkulast.egg-info/not-zip-safe
pkulast.egg-info/requires.txt
pkulast.egg-info/top_level.txt
pkulast/atmosphere/__init__.py
pkulast/atmosphere/correction.py
pkulast/atmosphere/profile.py
pkulast/etc/algorithm.yaml
pkulast/etc/config.yaml
pkulast/etc/profiles.yaml
pkulast/raster/__init__.py
pkulast/raster/applier.py
pkulast/raster/calcstats.py
pkulast/raster/colortable.py
pkulast/raster/cuiprogress.py
pkulast/raster/downloader.py
pkulast/raster/fileinfo.py
pkulast/raster/imageio.py
pkulast/raster/imagereader.py
pkulast/raster/imagewriter.py
pkulast/raster/inputcollection.py
pkulast/raster/pixelgrid.py
pkulast/raster/rat.py
pkulast/raster/ratapplier.py
pkulast/raster/reader.py
pkulast/raster/readerinfo.py
pkulast/raster/vectorreader.py
pkulast/raster/cmdline/__init__.py
pkulast/raster/cmdline/calcstats.py
pkulast/raster/cmdline/printstats.py
pkulast/raster/parallel/__init__.py
pkulast/raster/parallel/cloudpickle.py
pkulast/raster/parallel/jobmanager.py
pkulast/raster/parallel/subproc.py
pkulast/raster/riostests/__init__.py
pkulast/raster/riostests/riostestutils.py
pkulast/raster/riostests/testavg.py
pkulast/raster/riostests/testavgmpi.py
pkulast/raster/riostests/testavgmulti.py
pkulast/raster/riostests/testcolortable.py
pkulast/raster/riostests/testcoords.py
pkulast/raster/riostests/testlayerselection.py
pkulast/raster/riostests/testrat.py
pkulast/raster/riostests/testratapplier.py
pkulast/raster/riostests/testratcolortable.py
pkulast/raster/riostests/testratstats.py
pkulast/raster/riostests/testresample.py
pkulast/raster/riostests/teststats.py
pkulast/raster/riostests/testvector.py
pkulast/remote/__init__.py
pkulast/remote/observer.py
pkulast/remote/sensor.py
pkulast/retrieval/__init__.py
pkulast/retrieval/algorithm.py
pkulast/retrieval/coefficient.py
pkulast/retrieval/interface.py
pkulast/rtm/__init__.py
pkulast/rtm/model.py
pkulast/rtm/parallel.py
pkulast/surface/__init__.py
pkulast/surface/emissivity.py
