Metadata-Version: 2.1
Name: pkulast
Version: 0.1.6
Summary: PKU LAnd Surface Temperature(PKULAST)
Home-page: https://github.com/tirzhu/pkulast_stable
Author: Jinshun Zhu
Author-email: tirzhu@gmail.com
License: LGPL License
Keywords: modtran infrared
Platform: any
Requires-Python: >=3.7
Provides-Extra: doc
Provides-Extra: all
License-File: LICENSE.txt
